swh/loader/cli.py
swh/loader/exception.py
swh/loader/py.typed
swh/loader/pytest_plugin.py
swh/loader/core/__init__.py
swh/loader/core/converters.py
swh/loader/core/loader.py
swh/loader/core/metadata_fetchers.py
swh/loader/core/tasks.py
swh/loader/core/utils.py
swh/loader/core/tests/__init__.py
swh/loader/core/tests/conftest.py
swh/loader/core/tests/dummy_loader.py
swh/loader/core/tests/test_converters.py
swh/loader/core/tests/test_loader.py
swh/loader/core/tests/test_tasks.py
swh/loader/core/tests/test_utils.py
swh/loader/core/tests/data/https_common-lisp.net/project_asdf_archives_asdf-3.3.5.lisp
swh/loader/core/tests/data/https_example.org/archives_dummy-hello-with-executable.tar.gz
swh/loader/core/tests/data/https_example.org/archives_dummy-hello.tar.gz
swh/loader/core/tests/data/https_example.org/tarball.nar.xz
swh/loader/core/tests/data/https_example.org/test-executable.sh
swh/loader/package/loader.py
swh/loader/package/arch/__init__.py
swh/loader/package/arch/loader.py
swh/loader/package/arch/tasks.py
swh/loader/package/arch/tests/__init__.py
swh/loader/package/arch/tests/test_arch.py
swh/loader/package/arch/tests/test_tasks.py
swh/loader/package/arch/tests/data/fake_arch.sh
swh/loader/package/arch/tests/data/https_archive.archlinux.org/packages_d_dialog_dialog-1:1.3_20190211-1-x86_64.pkg.tar.xz
swh/loader/package/arch/tests/data/https_archive.archlinux.org/packages_d_dialog_dialog-1:1.3_20220414-1-x86_64.pkg.tar.zst
swh/loader/package/arch/tests/data/https_uk.mirror.archlinuxarm.org/aarch64_core_gzip-1.12-1-aarch64.pkg.tar.xz
swh/loader/package/archive/__init__.py
swh/loader/package/archive/loader.py
swh/loader/package/archive/tasks.py
swh/loader/package/archive/tests/__init__.py
swh/loader/package/archive/tests/test_archive.py
swh/loader/package/archive/tests/test_tasks.py
swh/loader/package/archive/tests/data/not_gzipped_tarball.tar.gz
swh/loader/package/archive/tests/data/https_ftp.gnu.org/gnu_8sync_8sync-0.1.0.tar.gz
swh_loader_core-5.24.2.dist-info/licenses/AUTHORS
swh_loader_core-5.24.2.dist-info/licenses/LICENSE
swh_loader_core-5.24.2.dist-info/METADATA
swh_loader_core-5.24.2.dist-info/WHEEL
swh_loader_core-5.24.2.dist-info/entry_points.txt
swh_loader_core-5.24.2.dist-info/top_level.txt
swh_loader_core-5.24.2.dist-info/RECORD
