Metadata-Version: 2.4
Name: swh.loader.core
Version: 5.24.2
Summary: Software Heritage core and package loaders
Author-email: Software Heritage developers <swh-devel@inria.fr>
Project-URL: Homepage, https://gitlab.softwareheritage.org/swh/devel/swh-loader-core
Project-URL: Bug Reports, https://gitlab.softwareheritage.org/swh/devel/swh-loader-core/-/issues
Project-URL: Funding, https://www.softwareheritage.org/donate
Project-URL: Documentation, https://docs.softwareheritage.org/devel/swh-loader-core/
Project-URL: Source, https://gitlab.softwareheritage.org/swh/devel/swh-loader-core.git
Classifier: Programming Language :: Python :: 3
Classifier: Intended Audience :: Developers
Classifier: License :: OSI Approved :: GNU General Public License v3 (GPLv3)
Classifier: Operating System :: OS Independent
Classifier: Development Status :: 5 - Production/Stable
Classifier: Programming Language :: Python :: Implementation :: CPython
Classifier: Programming Language :: Python :: Implementation :: PyPy
Requires-Python: >=3.10
License-File: LICENSE
License-File: AUTHORS
Requires-Dist: beautifulsoup4
Requires-Dist: chardet
Requires-Dist: psutil
Requires-Dist: requests
Requires-Dist: iso8601
Requires-Dist: looseversion
Requires-Dist: lxml
Requires-Dist: pkginfo
Requires-Dist: python-debian
Requires-Dist: python-dateutil
Requires-Dist: tenacity>=8.4.2
Requires-Dist: typing-extensions
Requires-Dist: toml
Requires-Dist: swh.core>=4.5.3
Requires-Dist: swh.model>=8.1.0
Requires-Dist: swh.objstorage>=0.2.2
Requires-Dist: swh.scheduler>=2.3.0
Requires-Dist: swh.storage>=2.4.1
Provides-Extra: testing
Requires-Dist: celery-types; extra == "testing"
Requires-Dist: pytest; extra == "testing"
Requires-Dist: pytest-mock; extra == "testing"
Requires-Dist: requests_mock>=1.11.0; extra == "testing"
Requires-Dist: urllib3; extra == "testing"
Requires-Dist: swh-core[testing]; extra == "testing"
Requires-Dist: swh.scheduler[pytest]>=3.1.0; extra == "testing"
Requires-Dist: swh.storage[pytest]>=3.1.0; extra == "testing"
Requires-Dist: swh-vault>=1.12.2; extra == "testing"
Requires-Dist: types-python-dateutil; extra == "testing"
Requires-Dist: types-psutil; extra == "testing"
Requires-Dist: types-pyyaml; extra == "testing"
Requires-Dist: types-requests; extra == "testing"
Requires-Dist: types-toml; extra == "testing"
Dynamic: license-file
